task3/counter.sv
module counter #(
    parameter WIDTH = 8
)(
    // interface signals
    input logic                 clk,        // clock signal
    input logic                 rst,        // reset signal
    input logic                 ld,         // load counter from data
    input logic [WIDTH-1:0]     v,          // value to preload
    output logic [WIDTH-1:0]    count,      // count output
);

always_ff @ (posedge clk)
    if (rst)        count <= {WIDTH{1'b0}};
    else            count <= ld ? count + {{WIDTH-1{1'b0}}, 1'b1} : count;      // when load is asserted increment the count by 1, otherwise return the current value of the count

endmodule

task3/counter.vcd
$version Generated by VerilatedVcd $end
$date Wed Dec  7 19:24:20 2022 $end
$timescale 1ps $end

 $scope module TOP $end
  $var wire  1 # clk $end
  $var wire  8 ' count [7:0] $end
  $var wire  1 % ld $end
  $var wire  1 $ rst $end
  $var wire  8 & v [7:0] $end
  $scope module counter $end
   $var wire 32 ( WIDTH [31:0] $end
   $var wire  1 # clk $end
   $var wire  8 ' count [7:0] $end
   $var wire  1 % ld $end
   $var wire  1 $ rst $end
   $var wire  8 & v [7:0] $end
  $upscope $end
 $upscope $end
$enddefinitions $end


#0
1#
1$
0%
b00000000 &
b00000000 '
b00000000000000000000000000001000 (
#1
0#
#2
1#
#3
0#
#4
1#
#5
0#
#6
1#
0$
#7
0#
#8
1#
#9
0#
#10
1#
#11
0#
#12
1#
#13
0#
#14
1#
#15
0#
#16
1#
#17
0#
#18
1#
#19
0#
#20
1#
#21
0#
#22
1#
#23
0#
#24
1#
#25
0#
#26
1#
#27
0#
#28
1#
#29
0#
#30
1#
#31
0#
#32
1#
1$
#33
0#
#34
1#
0$
#35
0#
#36
1#
#37
0#
#38
1#
1%
#39
0#
#40
1#
0%
b00000001 '
#41
0#
#42
1#
1%
#43
0#
#44
1#
b00000010 '
#45
0#
#46
1#
0%
b00000011 '
#47
0#
#48
1#
#49
0#
#50
1#
1%
#51
0#
#52
1#
0%
b00000100 '
#53
0#
#54
1#
#55
0#
#56
1#
#57
0#
#58
1#
#59
0#
#60
1#
#61
0#
#62
1#
1%
#63
0#
#64
1#
0%
b00000101 '
#65
0#
#66
1#
1%
#67
0#
#68
1#
b00000110 '
#69
0#
#70
1#
0%
b00000111 '
#71
0#
#72
1#
1%
#73
0#
#74
1#
b00001000 '
#75
0#
#76
1#
0%
b00001001 '
